[
    {
        "image_id": "politics_001",
        "question": "ছবিতে জনতার সামনে ভাষণ দিচ্ছেন যিনি, তিনি বাংলাদেশের রাজনীতিতে কী নামে পরিচিত?",
        "answer": "জাতির পিতা"
    },
    {
        "image_id": "politics_002",
        "question": "ছবির ভাষণ কোন স্থানে দেওয়া হয়েছিল?",
        "answer": "সোহরাওয়ার্দী উদ্যান"
    },
    {
        "image_id": "politics_003",
        "question": "ছবির লোকটি কোন পদে দায়িত্ব পালন করেছিলেন?",
        "answer": "প্রধানমন্ত্রী"
    },
    {
        "image_id": "politics_004",
        "question": "ছবির লোকটি কোন পদে ছিলেন?",
        "answer": "প্রেসিডেন্ট"
    },
    {
        "image_id": "politics_005",
        "question": "ছবির নেত্রী কোন দলের প্রধান?",
        "answer": "আওয়ামী লীগ"
    },
    {
        "image_id": "politics_006",
        "question": "ছবির নেত্রী কোন দলের প্রধান?",
        "answer": "বিএনপি"
    }
]