[
    {
        "image_id": "achievement_001",
        "question": "ছবিতে নারী ফুটবল দল ট্রফি হাতে উদযাপন করছে। তারা কোন টুর্নামেন্ট জিতেছে?",
        "answer": "সাফ নারী চ্যাম্পিয়নশিপ"
    },
    {
        "image_id": "achievement_002",
        "question": "এই ছবির মানুষটি কিসের জন্য বিখ্যাত?",
        "answer": "দক্ষিণ এশিয়ার প্রথম দাবা গ্র্যান্ডমাস্টার।"
    },
    {
        "image_id": "achievement_003",
        "question": "ইউনিভার্সিটি রোভার চ্যালেঞ্জে তারা এশিয়ায় কোন স্থান অর্জন করেছে?",
        "answer": "পুরো এশিয়ায় প্রথম স্থান।"
    },
    {
        "image_id": "achievement_004",
        "question": "এই ব্যক্তি কোন বছরে নোবেল পুরস্কার পেয়েছিলেন?",
        "answer": "২০০৬ সালে।"
    }
]